decam_lib/__init__.py
decam_lib/decam_processing.py
decam_lib/config/.DS_Store
decam_lib/config/__init__.py
decam_lib/config/default.param
decam_lib/config/default.psfex
decam_lib/config/default.sex
decam_lib/config/default.swarp
decam_lib/config/default_decam.psfex
decam_lib/config/default_psf.param
decam_lib/config/default_psf.sex
decamagwake-0.1.2.dist-info/METADATA
decamagwake-0.1.2.dist-info/WHEEL
decamagwake-0.1.2.dist-info/top_level.txt
decamagwake-0.1.2.dist-info/RECORD
