Metadata-Version: 2.1
Name: decamagwake
Version: 0.1.2
Summary: Testing installation of Package
Home-page: https://github.com/fawkez/magwake
Author: Manuel Cavieres
Author-email: mncavieres@uc.cl
License: MIT
Classifier: Intended Audience :: Developers
Classifier: License :: OSI Approved :: MIT License
Classifier: Programming Language :: Python
Classifier: Programming Language :: Python :: 3
Classifier: Programming Language :: Python :: 3.6
Classifier: Programming Language :: Python :: 3.7
Classifier: Programming Language :: Python :: 3.8
Classifier: Programming Language :: Python :: 3.9
Classifier: Operating System :: OS Independent
